sphinxcontrib/cheeseshop.py
sphinxcontrib_cheeseshop-0.3.dist-info/WHEEL
sphinxcontrib_cheeseshop-0.3.dist-info/METADATA
sphinxcontrib_cheeseshop-0.3.dist-info/RECORD
